{"ref": "DLR5L17N51173", "numero": "4706", "date": "2025-12-10", "nbVotants": 110, "votes": [{"acteurRef": "PA794434", "groupe": "RN", "position": "pour", "delegation": false}, {"acteurRef": "PA841645", "groupe": "RN", "position": "pour", "delegation": false}, {"acteurRef": "PA794886", "groupe": "RN", "position": "pour", "delegation": false}, {"acteurRef": "PA794762", "groupe": "RN", "position": "pour", "delegation": false}, {"acteurRef": "PA840135", "groupe": "RN", "position": "pour", "delegation": false}, {"acteurRef": "PA840143", "groupe": "RN", "position": "pour", "delegation": false}, {"acteurRef": "PA841737", "groupe": "RN", "position": "pour", "delegation": false}, {"acteurRef": "PA793832", "groupe": "RN", "position": "pour", "delegation": false}, {"acteurRef": "PA795778", "groupe": "RN", "position": "pour", "delegation": false}, {"acteurRef": "PA794502", "groupe": "RN", "position": "pour", "delegation": true}, {"acteurRef": "PA794946", "groupe": "RN", "position": "pour", "delegation": true}, {"acteurRef": "PA841451", "groupe": "RN", "position": "pour", "delegation": false}, {"acteurRef": "PA795900", "groupe": "RN", "position": "pour", "delegation": false}, {"acteurRef": "PA842085", "groupe": "RN", "position": "pour", "delegation": false}, {"acteurRef": "PA794598", "groupe": "RN", "position": "pour", "delegation": false}, {"acteurRef": "PA840857", "groupe": "RN", "position": "pour", "delegation": true}, {"acteurRef": "PA793672", "groupe": "RN", "position": "pour", "delegation": false}, {"acteurRef": "PA841587", "groupe": "RN", "position": "pour", "delegation": false}, {"acteurRef": "PA840837", "groupe": "RN", "position": "pour", "delegation": false}, {"acteurRef": "PA793696", "groupe": "RN", "position": "pour", "delegation": false}, {"acteurRef": "PA841199", "groupe": "RN", "position": "pour", "delegation": false}, {"acteurRef": "PA793656", "groupe": "RN", "position": "pour", "delegation": false}, {"acteurRef": "PA793230", "groupe": "RN", "position": "pour", "delegation": true}, {"acteurRef": "PA795410", "groupe": "RN", "position": "pour", "delegation": false}, {"acteurRef": "PA720468", "groupe": "RN", "position": "non-votant", "delegation": false}, {"acteurRef": "PA606507", "groupe": "EPR", "position": "pour", "delegation": false}, {"acteurRef": "PA794330", "groupe": "EPR", "position": "pour", "delegation": false}, {"acteurRef": "PA719890", "groupe": "EPR", "position": "pour", "delegation": false}, {"acteurRef": "PA842311", "groupe": "EPR", "position": "pour", "delegation": false}, {"acteurRef": "PA720154", "groupe": "EPR", "position": "pour", "delegation": false}, {"acteurRef": "PA840235", "groupe": "EPR", "position": "pour", "delegation": false}, {"acteurRef": "PA722366", "groupe": "EPR", "position": "pour", "delegation": false}, {"acteurRef": "PA721024", "groupe": "EPR", "position": "pour", "delegation": false}, {"acteurRef": "PA757225", "groupe": "EPR", "position": "pour", "delegation": false}, {"acteurRef": "PA2960", "groupe": "EPR", "position": "pour", "delegation": true}, {"acteurRef": "PA795046", "groupe": "EPR", "position": "pour", "delegation": false}, {"acteurRef": "PA842147", "groupe": "EPR", "position": "pour", "delegation": false}, {"acteurRef": "PA719372", "groupe": "EPR", "position": "pour", "delegation": false}, {"acteurRef": "PA720022", "groupe": "EPR", "position": "pour", "delegation": false}, {"acteurRef": "PA719412", "groupe": "EPR", "position": "pour", "delegation": false}, {"acteurRef": "PA720342", "groupe": "EPR", "position": "pour", "delegation": false}, {"acteurRef": "PA794206", "groupe": "EPR", "position": "pour", "delegation": true}, {"acteurRef": "PA719632", "groupe": "EPR", "position": "pour", "delegation": false}, {"acteurRef": "PA795402", "groupe": "EPR", "position": "pour", "delegation": false}, {"acteurRef": "PA795326", "groupe": "EPR", "position": "pour", "delegation": false}, {"acteurRef": "PA721908", "groupe": "EPR", "position": "non-votant", "delegation": false}, {"acteurRef": "PA795228", "groupe": "LFI", "position": "contre", "delegation": false}, {"acteurRef": "PA794138", "groupe": "LFI", "position": "contre", "delegation": false}, {"acteurRef": "PA793772", "groupe": "LFI", "position": "contre", "delegation": false}, {"acteurRef": "PA841023", "groupe": "LFI", "position": "contre", "delegation": false}, {"acteurRef": "PA793912", "groupe": "LFI", "position": "contre", "delegation": false}, {"acteurRef": "PA794786", "groupe": "LFI", "position": "contre", "delegation": false}, {"acteurRef": "PA794870", "groupe": "LFI", "position": "contre", "delegation": false}, {"acteurRef": "PA796070", "groupe": "LFI", "position": "contre", "delegation": false}, {"acteurRef": "PA841845", "groupe": "LFI", "position": "contre", "delegation": true}, {"acteurRef": "PA795982", "groupe": "LFI", "position": "contre", "delegation": false}, {"acteurRef": "PA720952", "groupe": "LFI", "position": "contre", "delegation": false}, {"acteurRef": "PA720846", "groupe": "LFI", "position": "contre", "delegation": false}, {"acteurRef": "PA795672", "groupe": "LFI", "position": "contre", "delegation": true}, {"acteurRef": "PA795108", "groupe": "LFI", "position": "contre", "delegation": true}, {"acteurRef": "PA841215", "groupe": "LFI", "position": "contre", "delegation": false}, {"acteurRef": "PA610654", "groupe": "LFI", "position": "contre", "delegation": false}, {"acteurRef": "PA795762", "groupe": "SOC", "position": "contre", "delegation": false}, {"acteurRef": "PA841633", "groupe": "SOC", "position": "contre", "delegation": false}, {"acteurRef": "PA774958", "groupe": "SOC", "position": "contre", "delegation": false}, {"acteurRef": "PA840793", "groupe": "SOC", "position": "contre", "delegation": false}, {"acteurRef": "PA841327", "groupe": "SOC", "position": "contre", "delegation": false}, {"acteurRef": "PA718884", "groupe": "DR", "position": "pour", "delegation": true}, {"acteurRef": "PA722390", "groupe": "DR", "position": "pour", "delegation": false}, {"acteurRef": "PA712015", "groupe": "DR", "position": "pour", "delegation": false}, {"acteurRef": "PA840979", "groupe": "DR", "position": "pour", "delegation": false}, {"acteurRef": "PA695512", "groupe": "DR", "position": "pour", "delegation": false}, {"acteurRef": "PA841507", "groupe": "ECO", "position": "contre", "delegation": false}, {"acteurRef": "PA842013", "groupe": "ECO", "position": "contre", "delegation": false}, {"acteurRef": "PA840947", "groupe": "ECO", "position": "contre", "delegation": false}, {"acteurRef": "PA793708", "groupe": "ECO", "position": "contre", "delegation": false}, {"acteurRef": "PA2940", "groupe": "ECO", "position": "contre", "delegation": false}, {"acteurRef": "PA795258", "groupe": "DEM", "position": "pour", "delegation": false}, {"acteurRef": "PA720038", "groupe": "DEM", "position": "pour", "delegation": true}, {"acteurRef": "PA794702", "groupe": "DEM", "position": "pour", "delegation": true}, {"acteurRef": "PA795100", "groupe": "DEM", "position": "pour", "delegation": false}, {"acteurRef": "PA719640", "groupe": "DEM", "position": "pour", "delegation": false}, {"acteurRef": "PA720720", "groupe": "DEM", "position": "pour", "delegation": false}, {"acteurRef": "PA795124", "groupe": "DEM", "position": "pour", "delegation": false}, {"acteurRef": "PA795278", "groupe": "HOR", "position": "pour", "delegation": true}, {"acteurRef": "PA719052", "groupe": "HOR", "position": "pour", "delegation": false}, {"acteurRef": "PA720138", "groupe": "HOR", "position": "pour", "delegation": false}, {"acteurRef": "PA722336", "groupe": "HOR", "position": "pour", "delegation": false}, {"acteurRef": "PA794466", "groupe": "HOR", "position": "pour", "delegation": false}, {"acteurRef": "PA794430", "groupe": "HOR", "position": "pour", "delegation": false}, {"acteurRef": "PA842183", "groupe": "HOR", "position": "pour", "delegation": false}, {"acteurRef": "PA840817", "groupe": "LIOT", "position": "pour", "delegation": false}, {"acteurRef": "PA942", "groupe": "LIOT", "position": "pour", "delegation": false}, {"acteurRef": "PA841359", "groupe": "LIOT", "position": "pour", "delegation": false}, {"acteurRef": "PA795244", "groupe": "LIOT", "position": "pour", "delegation": false}, {"acteurRef": "PA720976", "groupe": "LIOT", "position": "pour", "delegation": false}, {"acteurRef": "PA721486", "groupe": "LIOT", "position": "pour", "delegation": false}, {"acteurRef": "PA721110", "groupe": "LIOT", "position": "pour", "delegation": false}, {"acteurRef": "PA793796", "groupe": "LIOT", "position": "pour", "delegation": false}, {"acteurRef": "PA796078", "groupe": "LIOT", "position": "pour", "delegation": false}, {"acteurRef": "PA793214", "groupe": "LIOT", "position": "pour", "delegation": false}, {"acteurRef": "PA795868", "groupe": "GDR", "position": "contre", "delegation": false}, {"acteurRef": "PA335612", "groupe": "GDR", "position": "contre", "delegation": false}, {"acteurRef": "PA796010", "groupe": "GDR", "position": "contre", "delegation": false}, {"acteurRef": "PA795820", "groupe": "GDR", "position": "contre", "delegation": false}, {"acteurRef": "PA795240", "groupe": "GDR", "position": "contre", "delegation": false}, {"acteurRef": "PA842299", "groupe": "GDR", "position": "contre", "delegation": false}, {"acteurRef": "PA840701", "groupe": "UDR", "position": "pour", "delegation": false}, {"acteurRef": "PA841973", "groupe": "UDR", "position": "pour", "delegation": false}, {"acteurRef": "PA569", "groupe": "AUTRE", "position": "pour", "delegation": false}]}