{"acteurRef": "PA703532", "nom": "Annick Billon", "groupe": "", "circo": null, "ministere": "", "nbVotes": 0, "compte": {"pour": 0, "contre": 0, "abstention": 0, "non-votant": 0}, "parDelegation": 0, "votes": [], "textesDeposes": [{"ref": "DLR5L17N51987", "date": "2026-04-10", "titre": "Proposition de loi visant à permettre aux salariés de certains établissements et services de travailler le 1er mai", "statut": "adopté", "type": "Proposition de loi"}, {"ref": "DLR5L16N49843", "date": "2025-02-10", "titre": "Proposition de loi visant à permettre l'élection du maire d'une commune nouvelle en cas de conseil municipal incomplet", "statut": "adopté", "type": "Proposition de loi"}]}